{
  "id": "modules/fundamentals/tier_apps",
  "title": "tier_apps",
  "description": "",
  "source": "@site/docs/modules/fundamentals/3_tier_apps.md",
  "sourceDirName": "modules/fundamentals",
  "slug": "/modules/fundamentals/tier_apps",
  "permalink": "/docs/modules/fundamentals/tier_apps",
  "draft": false,
  "unlisted": false,
  "editUrl": "https://github.com/dixonaws/aws-cloudops/tree/main/packages/create-docusaurus/templates/shared/docs/modules/fundamentals/3_tier_apps.md",
  "tags": [],
  "version": "current",
  "sidebarPosition": 6,
  "frontMatter": {
    "sidebar_label": "Building 3-tier Applications",
    "sidebar_position": 6
  },
  "sidebar": "modules",
  "previous": {
    "title": "Advanced Linux",
    "permalink": "/docs/modules/fundamentals/advanced_linux"
  },
  "next": {
    "title": "Cloud Administration",
    "permalink": "/docs/modules/cloud/"
  }
}