{
  "pluginId": "default",
  "version": "current",
  "label": "Next",
  "banner": null,
  "badge": false,
  "noIndex": false,
  "className": "docs-version-current",
  "isLast": true,
  "docsSidebars": {
    "mySidebar": [
      {
        "type": "link",
        "label": "Philosophy",
        "href": "/docs/philosophy",
        "docId": "philosophy",
        "unlisted": false
      },
      {
        "type": "link",
        "label": "Course Outline",
        "href": "/docs/outline",
        "docId": "outline",
        "unlisted": false
      },
      {
        "type": "category",
        "label": "Modules",
        "collapsible": true,
        "collapsed": true,
        "items": [
          {
            "type": "link",
            "label": "Linux Administration Basics",
            "href": "/docs/modules/linux",
            "docId": "modules/linux",
            "unlisted": false
          }
        ],
        "href": "/docs/category/modules"
      }
    ]
  },
  "docs": {
    "modules/linux": {
      "id": "modules/linux",
      "title": "linux",
      "description": "",
      "sidebar": "mySidebar"
    },
    "outline": {
      "id": "outline",
      "title": "Course Outline",
      "description": "This is not a coding bootcamp. We realize that you can search the internet and skill up",
      "sidebar": "mySidebar"
    },
    "philosophy": {
      "id": "philosophy",
      "title": "Philosophy",
      "description": "This is not a coding bootcamp. We realize that you can search the internet and skill up",
      "sidebar": "mySidebar"
    }
  }
}